setup.py
bin/sauron
bin/sauron-daemon
sauron/__init__.py
sauron.egg-info/PKG-INFO
sauron.egg-info/SOURCES.txt
sauron.egg-info/dependency_links.txt
sauron.egg-info/requires.txt
sauron.egg-info/top_level.txt
sauron/emitters/CampfireBot.py
sauron/emitters/CloudWatch.py
sauron/emitters/HTTPEndpoint.py
sauron/emitters/JabberBot.py
sauron/emitters/Twitter.py
sauron/emitters/__init__.py
sauron/metrics/DiskMetric.py
sauron/metrics/JSONPingMetric.py
sauron/metrics/LogMetric.py
sauron/metrics/MySQLMetric.py
sauron/metrics/PingMetric.py
sauron/metrics/PipeMetric.py
sauron/metrics/ProcMetric.py
sauron/metrics/RedisMetric.py
sauron/metrics/S3BucketMetric.py
sauron/metrics/ShellMetric.py
sauron/metrics/SphinxMetric.py
sauron/metrics/SystemMetric.py
sauron/metrics/__init__.py