Metadata-Version: 1.0
Name: sauron
Version: 0.1.2
Summary: An eye for monitoring, and pushing monitoring data
Home-page: http://github.com/seomoz/sauron/
Author: Dan Lecocq
Author-email: dan@seomoz.org
License: UNKNOWN
Keywords: monitoring,cloudwatch
Platform: UNKNOWN
Classifier: Programming Language :: Python
Classifier: Intended Audience :: Developers
Classifier: Topic :: Software Development :: Libraries :: Python Modules
